inertia/__init__.py
inertia/_config.py
inertia/_core.py
inertia/_exceptions.py
inertia/_props.py
inertia/_ssr.py
inertia/_utils.py
inertia/_vite.py
inertia/middleware.py
inertia/py.typed
inertia/django/__init__.py
inertia/django/apps.py
inertia/django/conf.py
inertia/django/middleware.py
inertia/django/response.py
inertia/django/shortcuts.py
inertia/django/templatetags/__init__.py
inertia/django/templatetags/inertia.py
inertia/fastapi/__init__.py
inertia/fastapi/experimental/__init__.py
inertia/fastapi/experimental/lifespan.py
cross_inertia-0.12.0.dist-info/METADATA
cross_inertia-0.12.0.dist-info/WHEEL
cross_inertia-0.12.0.dist-info/licenses/LICENSE
cross_inertia-0.12.0.dist-info/RECORD
