Metadata-Version: 2.4
Name: cross-inertia
Version: 0.12.0
Summary: Inertia.js adapter for Python web frameworks
Project-URL: Homepage, https://github.com/patrick91/cross-inertia
Project-URL: Documentation, https://inertia.patrick.wtf
Project-URL: Repository, https://github.com/patrick91/cross-inertia
Project-URL: Issues, https://github.com/patrick91/cross-inertia/issues
Author-email: Patrick Arminio <patrick.arminio@gmail.com>
License-File: LICENSE
Requires-Python: >=3.10
Requires-Dist: httpx>=0.28.0
Requires-Dist: itsdangerous>=2.2.0
Requires-Dist: lia-web>=0.2.3
Provides-Extra: all
Requires-Dist: django>=4.2; extra == 'all'
Requires-Dist: fastapi>=0.100.0; extra == 'all'
Requires-Dist: jinja2>=3.0.0; extra == 'all'
Provides-Extra: django
Requires-Dist: django>=4.2; extra == 'django'
Provides-Extra: fastapi
Requires-Dist: fastapi>=0.100.0; extra == 'fastapi'
Requires-Dist: jinja2>=3.0.0; extra == 'fastapi'
